airobot/__init__.py
airobot-0.1.3.dist-info/LICENSE
airobot-0.1.3.dist-info/METADATA
airobot-0.1.3.dist-info/WHEEL
airobot-0.1.3.dist-info/top_level.txt
airobot-0.1.3.dist-info/RECORD
