Metadata-Version: 2.1
Name: airobot
Version: 0.1.3
Summary: aichat
Home-page: https://github.com/August/sampleproject
Author: August
Author-email: august@163.com
License: UNKNOWN
Platform: UNKNOWN
Classifier: Programming Language :: Python :: 3
Classifier: License :: OSI Approved :: MIT License
Classifier: Operating System :: OS Independent
Requires-Dist: requests
